{"id":18945728,"id_str":"18945728","name":"InformationWeek SMB","screen_name":"InfoWeekSMB","location":"San Francisco, CA","profile_location":null,"description":"The Technology Resource For Small & Midsize Businesses. (previously known as bMighty)","url":"http:\/\/t.co\/6k0uQvytxu","entities":{"url":{"urls":[{"url":"http:\/\/t.co\/6k0uQvytxu","expanded_url":"http:\/\/www.informationweek.com\/smb","display_url":"informationweek.com\/smb","indices":[0,22]}]},"description":{"urls":[]}},"protected":false,"followers_count":1766,"friends_count":7,"listed_count":118,"created_at":"Tue Jan 13 17:49:42 +0000 2009","favourites_count":2,"utc_offset":-28800,"time_zone":"Pacific Time (US & Canada)","geo_enabled":false,"verified":false,"statuses_count":4017,"lang":"en","status":{"created_at":"Fri May 01 23:42:33 +0000 2015","id":594285812017074176,"id_str":"594285812017074176","text":"No Articles Were Found... Visit Our Web Site for More Information http:\/\/t.co\/MsfzZ6gNyK","source":"\u003ca href=\"http:\/\/twitterfeed.com\" rel=\"nofollow\"\u003etwitterfeed\u003c\/a\u003e","truncated":false,"in_reply_to_status_id":null,"in_reply_to_status_id_str":null,"in_reply_to_user_id":null,"in_reply_to_user_id_str":null,"in_reply_to_screen_name":null,"geo":null,"coordinates":null,"place":null,"contributors":null,"is_quote_status":false,"retweet_count":0,"favorite_count":0,"entities":{"hashtags":[],"symbols":[],"user_mentions":[],"urls":[{"url":"http:\/\/t.co\/MsfzZ6gNyK","expanded_url":"http:\/\/ubm.io\/acfWgI","display_url":"ubm.io\/acfWgI","indices":[66,88]}]},"favorited":false,"retweeted":false,"possibly_sensitive":false,"lang":"en"},"contributors_enabled":false,"is_translator":false,"is_translation_enabled":false,"profile_background_color":"020303","profile_background_image_url":"http:\/\/abs.twimg.com\/images\/themes\/theme1\/bg.png","profile_background_image_url_https":"https:\/\/abs.twimg.com\/images\/themes\/theme1\/bg.png","profile_background_tile":false,"profile_image_url":"http:\/\/pbs.twimg.com\/profile_images\/1848851028\/SMB_twitter_normal.jpg","profile_image_url_https":"https:\/\/pbs.twimg.com\/profile_images\/1848851028\/SMB_twitter_normal.jpg","profile_link_color":"000000","profile_sidebar_border_color":"AD0513","profile_sidebar_fill_color":"AD0513","profile_text_color":"000000","profile_use_background_image":false,"has_extended_profile":false,"default_profile":false,"default_profile_image":false,"following":false,"follow_request_sent":false,"notifications":false}
