{"id":21618273,"id_str":"21618273","name":"Cindy Clifford","screen_name":"cindy8000","location":"Houston","profile_location":null,"description":"PR Pro, CityGal, Political Junkie, Newspaper and Magazine-aholic, Movie Buff, Bookstore Lover, Avid cupcake baker","url":"http:\/\/t.co\/GpcQaIgvkW","entities":{"url":{"urls":[{"url":"http:\/\/t.co\/GpcQaIgvkW","expanded_url":"http:\/\/www.thecliffordgroup.com","display_url":"thecliffordgroup.com","indices":[0,22]}]},"description":{"urls":[]}},"protected":false,"followers_count":1288,"friends_count":2003,"listed_count":37,"created_at":"Mon Feb 23 01:06:13 +0000 2009","favourites_count":417,"utc_offset":-21600,"time_zone":"Central Time (US & Canada)","geo_enabled":true,"verified":false,"statuses_count":7769,"lang":"en","status":{"created_at":"Mon Jan 25 16:34:37 +0000 2016","id":691660456465838081,"id_str":"691660456465838081","text":"RT @IAmMaryBenton: Dreams do come true. #mondaymotivation  https:\/\/t.co\/gqams32ICV","source":"\u003ca href=\"http:\/\/twitter.com\/download\/iphone\" rel=\"nofollow\"\u003eTwitter for iPhone\u003c\/a\u003e","truncated":false,"in_reply_to_status_id":null,"in_reply_to_status_id_str":null,"in_reply_to_user_id":null,"in_reply_to_user_id_str":null,"in_reply_to_screen_name":null,"geo":null,"coordinates":null,"place":null,"contributors":null,"retweeted_status":{"created_at":"Mon Jan 25 16:34:24 +0000 2016","id":691660402069889024,"id_str":"691660402069889024","text":"Dreams do come true. #mondaymotivation  https:\/\/t.co\/gqams32ICV","source":"\u003ca href=\"http:\/\/twitter.com\/download\/iphone\" rel=\"nofollow\"\u003eTwitter for iPhone\u003c\/a\u003e","truncated":false,"in_reply_to_status_id":null,"in_reply_to_status_id_str":null,"in_reply_to_user_id":null,"in_reply_to_user_id_str":null,"in_reply_to_screen_name":null,"geo":null,"coordinates":null,"place":{"id":"1c69a67ad480e1b1","url":"https:\/\/api.twitter.com\/1.1\/geo\/id\/1c69a67ad480e1b1.json","place_type":"city","name":"Houston","full_name":"Houston, TX","country_code":"US","country":"United States","contained_within":[],"bounding_box":{"type":"Polygon","coordinates":[[[-95.823268,29.522325],[-95.069705,29.522325],[-95.069705,30.1546646],[-95.823268,30.1546646]]]},"attributes":{}},"contributors":null,"quoted_status_id":691458656949268480,"quoted_status_id_str":"691458656949268480","is_quote_status":true,"retweet_count":2,"favorite_count":2,"entities":{"hashtags":[{"text":"mondaymotivation","indices":[21,38]}],"symbols":[],"user_mentions":[],"urls":[{"url":"https:\/\/t.co\/gqams32ICV","expanded_url":"https:\/\/twitter.com\/sonofbum\/status\/691458656949268480","display_url":"twitter.com\/sonofbum\/statu\u2026","indices":[40,63]}]},"favorited":false,"retweeted":false,"possibly_sensitive":false,"lang":"en"},"is_quote_status":true,"retweet_count":2,"favorite_count":0,"entities":{"hashtags":[{"text":"mondaymotivation","indices":[40,57]}],"symbols":[],"user_mentions":[{"screen_name":"IAmMaryBenton","name":"Mary Benton","id":38313524,"id_str":"38313524","indices":[3,17]}],"urls":[{"url":"https:\/\/t.co\/gqams32ICV","expanded_url":"https:\/\/twitter.com\/sonofbum\/status\/691458656949268480","display_url":"twitter.com\/sonofbum\/statu\u2026","indices":[59,82]}]},"favorited":false,"retweeted":false,"possibly_sensitive":false,"lang":"en"},"contributors_enabled":false,"is_translator":false,"is_translation_enabled":false,"profile_background_color":"352726","profile_background_image_url":"http:\/\/abs.twimg.com\/images\/themes\/theme5\/bg.gif","profile_background_image_url_https":"https:\/\/abs.twimg.com\/images\/themes\/theme5\/bg.gif","profile_background_tile":false,"profile_image_url":"http:\/\/pbs.twimg.com\/profile_images\/95688912\/Cindy_normal.jpg","profile_image_url_https":"https:\/\/pbs.twimg.com\/profile_images\/95688912\/Cindy_normal.jpg","profile_link_color":"D02B55","profile_sidebar_border_color":"829D5E","profile_sidebar_fill_color":"99CC33","profile_text_color":"3E4415","profile_use_background_image":true,"has_extended_profile":false,"default_profile":false,"default_profile_image":false,"following":false,"follow_request_sent":false,"notifications":false}
