{"id":226594115,"id_str":"226594115","name":"Levin Mejia","screen_name":"fourandthree","location":"St. John's, NL","profile_location":null,"description":"Designer Advocate @Shopify. Designer, maker, & founder of @eveyevents, @mightynote, & @gobeyondpixels. \u2764\ufe0f @sevinmejia","url":"https:\/\/t.co\/QCf88JWkCo","entities":{"url":{"urls":[{"url":"https:\/\/t.co\/QCf88JWkCo","expanded_url":"http:\/\/www.fourandthree.com","display_url":"fourandthree.com","indices":[0,23]}]},"description":{"urls":[]}},"protected":false,"followers_count":683,"friends_count":1334,"listed_count":64,"created_at":"Tue Dec 14 15:36:32 +0000 2010","favourites_count":2147,"utc_offset":null,"time_zone":null,"geo_enabled":true,"verified":false,"statuses_count":4903,"lang":"en","status":{"created_at":"Tue Jan 26 00:09:45 +0000 2016","id":691774992892174337,"id_str":"691774992892174337","text":"@TommyLee I would love to hang with you again! The talk sounds great. You never know.... \ud83d\ude09","source":"\u003ca href=\"http:\/\/twitter.com\/download\/iphone\" rel=\"nofollow\"\u003eTwitter for iPhone\u003c\/a\u003e","truncated":false,"in_reply_to_status_id":691773123679645698,"in_reply_to_status_id_str":"691773123679645698","in_reply_to_user_id":5541152,"in_reply_to_user_id_str":"5541152","in_reply_to_screen_name":"TommyLee","geo":null,"coordinates":null,"place":null,"contributors":null,"is_quote_status":false,"retweet_count":0,"favorite_count":3,"entities":{"hashtags":[],"symbols":[],"user_mentions":[{"screen_name":"TommyLee","name":"Tommy Lewis","id":5541152,"id_str":"5541152","indices":[0,9]}],"urls":[]},"favorited":false,"retweeted":false,"lang":"en"},"contributors_enabled":false,"is_translator":false,"is_translation_enabled":false,"profile_background_color":"F5EEE2","profile_background_image_url":"http:\/\/pbs.twimg.com\/profile_background_images\/312077316\/Unknown.png","profile_background_image_url_https":"https:\/\/pbs.twimg.com\/profile_background_images\/312077316\/Unknown.png","profile_background_tile":false,"profile_image_url":"http:\/\/pbs.twimg.com\/profile_images\/677282790057115648\/Wl6H-750_normal.jpg","profile_image_url_https":"https:\/\/pbs.twimg.com\/profile_images\/677282790057115648\/Wl6H-750_normal.jpg","profile_banner_url":"https:\/\/pbs.twimg.com\/profile_banners\/226594115\/1441465505","profile_link_color":"CD8B12","profile_sidebar_border_color":"FFFFFF","profile_sidebar_fill_color":"EFEFEF","profile_text_color":"333333","profile_use_background_image":false,"has_extended_profile":false,"default_profile":false,"default_profile_image":false,"following":false,"follow_request_sent":false,"notifications":false}
