{"id":27606060,"id_str":"27606060","name":"D_SNAPS","screen_name":"D_SNAPS","location":"Seattle, Wa","profile_location":null,"description":"#teamSNAPS","url":null,"entities":{"description":{"urls":[]}},"protected":false,"followers_count":235,"friends_count":524,"listed_count":0,"created_at":"Mon Mar 30 08:33:26 +0000 2009","favourites_count":17,"utc_offset":-28800,"time_zone":"Pacific Time (US & Canada)","geo_enabled":false,"verified":false,"statuses_count":5497,"lang":"en","status":{"created_at":"Tue Jan 19 19:11:06 +0000 2016","id":689525509215162370,"id_str":"689525509215162370","text":"RT @newsone: MISSING: New York City flight attendant, Sierra Shields, disappears https:\/\/t.co\/Ffgs7vSEDD https:\/\/t.co\/f3DOEQQrgI","source":"\u003ca href=\"http:\/\/stone.com\/Twittelator\" rel=\"nofollow\"\u003eTwittelator\u003c\/a\u003e","truncated":false,"in_reply_to_status_id":null,"in_reply_to_status_id_str":null,"in_reply_to_user_id":null,"in_reply_to_user_id_str":null,"in_reply_to_screen_name":null,"geo":null,"coordinates":null,"place":null,"contributors":null,"retweeted_status":{"created_at":"Tue Jan 19 15:46:43 +0000 2016","id":689474072019775488,"id_str":"689474072019775488","text":"MISSING: New York City flight attendant, Sierra Shields, disappears https:\/\/t.co\/Ffgs7vSEDD https:\/\/t.co\/f3DOEQQrgI","source":"\u003ca href=\"https:\/\/about.twitter.com\/products\/tweetdeck\" rel=\"nofollow\"\u003eTweetDeck\u003c\/a\u003e","truncated":false,"in_reply_to_status_id":null,"in_reply_to_status_id_str":null,"in_reply_to_user_id":null,"in_reply_to_user_id_str":null,"in_reply_to_screen_name":null,"geo":null,"coordinates":null,"place":null,"contributors":null,"is_quote_status":false,"retweet_count":135,"favorite_count":45,"entities":{"hashtags":[],"symbols":[],"user_mentions":[],"urls":[{"url":"https:\/\/t.co\/Ffgs7vSEDD","expanded_url":"http:\/\/bit.ly\/1Wr60h7","display_url":"bit.ly\/1Wr60h7","indices":[68,91]}],"media":[{"id":689474064289689600,"id_str":"689474064289689600","indices":[92,115],"media_url":"http:\/\/pbs.twimg.com\/media\/CZGBAivU8AAXzaE.jpg","media_url_https":"https:\/\/pbs.twimg.com\/media\/CZGBAivU8AAXzaE.jpg","url":"https:\/\/t.co\/f3DOEQQrgI","display_url":"pic.twitter.com\/f3DOEQQrgI","expanded_url":"http:\/\/twitter.com\/newsone\/status\/689474072019775488\/photo\/1","type":"photo","sizes":{"thumb":{"w":150,"h":150,"resize":"crop"},"large":{"w":300,"h":300,"resize":"fit"},"medium":{"w":300,"h":300,"resize":"fit"},"small":{"w":300,"h":300,"resize":"fit"}}}]},"extended_entities":{"media":[{"id":689474064289689600,"id_str":"689474064289689600","indices":[92,115],"media_url":"http:\/\/pbs.twimg.com\/media\/CZGBAivU8AAXzaE.jpg","media_url_https":"https:\/\/pbs.twimg.com\/media\/CZGBAivU8AAXzaE.jpg","url":"https:\/\/t.co\/f3DOEQQrgI","display_url":"pic.twitter.com\/f3DOEQQrgI","expanded_url":"http:\/\/twitter.com\/newsone\/status\/689474072019775488\/photo\/1","type":"photo","sizes":{"thumb":{"w":150,"h":150,"resize":"crop"},"large":{"w":300,"h":300,"resize":"fit"},"medium":{"w":300,"h":300,"resize":"fit"},"small":{"w":300,"h":300,"resize":"fit"}}}]},"favorited":false,"retweeted":false,"possibly_sensitive":false,"lang":"en"},"is_quote_status":false,"retweet_count":135,"favorite_count":0,"entities":{"hashtags":[],"symbols":[],"user_mentions":[{"screen_name":"newsone","name":"NewsOne","id":18197668,"id_str":"18197668","indices":[3,11]}],"urls":[{"url":"https:\/\/t.co\/Ffgs7vSEDD","expanded_url":"http:\/\/bit.ly\/1Wr60h7","display_url":"bit.ly\/1Wr60h7","indices":[81,104]}],"media":[{"id":689474064289689600,"id_str":"689474064289689600","indices":[105,128],"media_url":"http:\/\/pbs.twimg.com\/media\/CZGBAivU8AAXzaE.jpg","media_url_https":"https:\/\/pbs.twimg.com\/media\/CZGBAivU8AAXzaE.jpg","url":"https:\/\/t.co\/f3DOEQQrgI","display_url":"pic.twitter.com\/f3DOEQQrgI","expanded_url":"http:\/\/twitter.com\/newsone\/status\/689474072019775488\/photo\/1","type":"photo","sizes":{"thumb":{"w":150,"h":150,"resize":"crop"},"large":{"w":300,"h":300,"resize":"fit"},"medium":{"w":300,"h":300,"resize":"fit"},"small":{"w":300,"h":300,"resize":"fit"}},"source_status_id":689474072019775488,"source_status_id_str":"689474072019775488","source_user_id":18197668,"source_user_id_str":"18197668"}]},"extended_entities":{"media":[{"id":689474064289689600,"id_str":"689474064289689600","indices":[105,128],"media_url":"http:\/\/pbs.twimg.com\/media\/CZGBAivU8AAXzaE.jpg","media_url_https":"https:\/\/pbs.twimg.com\/media\/CZGBAivU8AAXzaE.jpg","url":"https:\/\/t.co\/f3DOEQQrgI","display_url":"pic.twitter.com\/f3DOEQQrgI","expanded_url":"http:\/\/twitter.com\/newsone\/status\/689474072019775488\/photo\/1","type":"photo","sizes":{"thumb":{"w":150,"h":150,"resize":"crop"},"large":{"w":300,"h":300,"resize":"fit"},"medium":{"w":300,"h":300,"resize":"fit"},"small":{"w":300,"h":300,"resize":"fit"}},"source_status_id":689474072019775488,"source_status_id_str":"689474072019775488","source_user_id":18197668,"source_user_id_str":"18197668"}]},"favorited":false,"retweeted":false,"possibly_sensitive":false,"lang":"en"},"contributors_enabled":false,"is_translator":false,"is_translation_enabled":false,"profile_background_color":"1A1B1F","profile_background_image_url":"http:\/\/abs.twimg.com\/images\/themes\/theme9\/bg.gif","profile_background_image_url_https":"https:\/\/abs.twimg.com\/images\/themes\/theme9\/bg.gif","profile_background_tile":false,"profile_image_url":"http:\/\/pbs.twimg.com\/profile_images\/1172640310\/l7sqW_normal.jpg","profile_image_url_https":"https:\/\/pbs.twimg.com\/profile_images\/1172640310\/l7sqW_normal.jpg","profile_link_color":"2FC2EF","profile_sidebar_border_color":"181A1E","profile_sidebar_fill_color":"252429","profile_text_color":"666666","profile_use_background_image":true,"has_extended_profile":false,"default_profile":false,"default_profile_image":false,"following":false,"follow_request_sent":false,"notifications":false}
