{"id":28504567,"id_str":"28504567","name":"BELLA","screen_name":"iLovetakia","location":"Minding my business ","profile_location":null,"description":"","url":null,"entities":{"description":{"urls":[]}},"protected":false,"followers_count":746,"friends_count":549,"listed_count":10,"created_at":"Fri Apr 03 04:37:23 +0000 2009","favourites_count":472,"utc_offset":-18000,"time_zone":"Eastern Time (US & Canada)","geo_enabled":true,"verified":false,"statuses_count":31707,"lang":"en","status":{"created_at":"Mon Jan 25 20:52:28 +0000 2016","id":691725343623876610,"id_str":"691725343623876610","text":"Shit just roll off my shoulders so easily...ion give af about nun on nun","source":"\u003ca href=\"http:\/\/twitter.com\/download\/iphone\" rel=\"nofollow\"\u003eTwitter for iPhone\u003c\/a\u003e","truncated":false,"in_reply_to_status_id":null,"in_reply_to_status_id_str":null,"in_reply_to_user_id":null,"in_reply_to_user_id_str":null,"in_reply_to_screen_name":null,"geo":null,"coordinates":null,"place":null,"contributors":null,"is_quote_status":false,"retweet_count":0,"favorite_count":0,"entities":{"hashtags":[],"symbols":[],"user_mentions":[],"urls":[]},"favorited":false,"retweeted":false,"lang":"en"},"contributors_enabled":false,"is_translator":false,"is_translation_enabled":false,"profile_background_color":"C0DEED","profile_background_image_url":"http:\/\/abs.twimg.com\/images\/themes\/theme1\/bg.png","profile_background_image_url_https":"https:\/\/abs.twimg.com\/images\/themes\/theme1\/bg.png","profile_background_tile":false,"profile_image_url":"http:\/\/pbs.twimg.com\/profile_images\/669225017058729984\/zP4NCl1C_normal.jpg","profile_image_url_https":"https:\/\/pbs.twimg.com\/profile_images\/669225017058729984\/zP4NCl1C_normal.jpg","profile_banner_url":"https:\/\/pbs.twimg.com\/profile_banners\/28504567\/1451343893","profile_link_color":"0084B4","profile_sidebar_border_color":"C0DEED","profile_sidebar_fill_color":"DDEEF6","profile_text_color":"333333","profile_use_background_image":true,"has_extended_profile":false,"default_profile":true,"default_profile_image":false,"following":false,"follow_request_sent":false,"notifications":false}
