{"id":303079893,"id_str":"303079893","name":"Chris Lowe","screen_name":"chriswglowe","location":"Hong Kong & UK","profile_location":null,"description":"Autumn body, spring mind: ENTJ Belbin Plant & Motivating Director - Love playing my Gibson Les Paul thru my Line 6 Vetta at volume 11","url":null,"entities":{"description":{"urls":[]}},"protected":false,"followers_count":111,"friends_count":284,"listed_count":4,"created_at":"Sun May 22 08:19:21 +0000 2011","favourites_count":51,"utc_offset":null,"time_zone":null,"geo_enabled":true,"verified":false,"statuses_count":1665,"lang":"en","status":{"created_at":"Sat Jan 23 14:04:56 +0000 2016","id":690898011476598784,"id_str":"690898011476598784","text":"RT @Wotamoron: Watch her leg at the end \ud83d\ude02 https:\/\/t.co\/Gtz15AFz6K","source":"\u003ca href=\"http:\/\/twitter.com\/download\/android\" rel=\"nofollow\"\u003eTwitter for Android\u003c\/a\u003e","truncated":false,"in_reply_to_status_id":null,"in_reply_to_status_id_str":null,"in_reply_to_user_id":null,"in_reply_to_user_id_str":null,"in_reply_to_screen_name":null,"geo":null,"coordinates":null,"place":null,"contributors":null,"retweeted_status":{"created_at":"Wed Jan 20 11:10:27 +0000 2016","id":689766935270158336,"id_str":"689766935270158336","text":"Watch her leg at the end \ud83d\ude02 https:\/\/t.co\/Gtz15AFz6K","source":"\u003ca href=\"http:\/\/twitter.com\/download\/iphone\" rel=\"nofollow\"\u003eTwitter for iPhone\u003c\/a\u003e","truncated":false,"in_reply_to_status_id":null,"in_reply_to_status_id_str":null,"in_reply_to_user_id":null,"in_reply_to_user_id_str":null,"in_reply_to_screen_name":null,"geo":null,"coordinates":null,"place":null,"contributors":null,"is_quote_status":false,"retweet_count":475,"favorite_count":488,"entities":{"hashtags":[],"symbols":[],"user_mentions":[],"urls":[],"media":[{"id":689766815858302977,"id_str":"689766815858302977","indices":[27,50],"media_url":"http:\/\/pbs.twimg.com\/tweet_video_thumb\/CZKLQ7UWIAECtYe.png","media_url_https":"https:\/\/pbs.twimg.com\/tweet_video_thumb\/CZKLQ7UWIAECtYe.png","url":"https:\/\/t.co\/Gtz15AFz6K","display_url":"pic.twitter.com\/Gtz15AFz6K","expanded_url":"http:\/\/twitter.com\/Wotamoron\/status\/689766935270158336\/photo\/1","type":"photo","sizes":{"medium":{"w":256,"h":274,"resize":"fit"},"small":{"w":256,"h":274,"resize":"fit"},"thumb":{"w":150,"h":150,"resize":"crop"},"large":{"w":256,"h":274,"resize":"fit"}}}]},"extended_entities":{"media":[{"id":689766815858302977,"id_str":"689766815858302977","indices":[27,50],"media_url":"http:\/\/pbs.twimg.com\/tweet_video_thumb\/CZKLQ7UWIAECtYe.png","media_url_https":"https:\/\/pbs.twimg.com\/tweet_video_thumb\/CZKLQ7UWIAECtYe.png","url":"https:\/\/t.co\/Gtz15AFz6K","display_url":"pic.twitter.com\/Gtz15AFz6K","expanded_url":"http:\/\/twitter.com\/Wotamoron\/status\/689766935270158336\/photo\/1","type":"animated_gif","sizes":{"medium":{"w":256,"h":274,"resize":"fit"},"small":{"w":256,"h":274,"resize":"fit"},"thumb":{"w":150,"h":150,"resize":"crop"},"large":{"w":256,"h":274,"resize":"fit"}},"video_info":{"aspect_ratio":[128,137],"variants":[{"bitrate":0,"content_type":"video\/mp4","url":"https:\/\/pbs.twimg.com\/tweet_video\/CZKLQ7UWIAECtYe.mp4"}]}}]},"favorited":false,"retweeted":false,"possibly_sensitive":false,"lang":"en"},"is_quote_status":false,"retweet_count":475,"favorite_count":0,"entities":{"hashtags":[],"symbols":[],"user_mentions":[{"screen_name":"Wotamoron","name":"WOT A MORON","id":3079307777,"id_str":"3079307777","indices":[3,13]}],"urls":[],"media":[{"id":689766815858302977,"id_str":"689766815858302977","indices":[42,65],"media_url":"http:\/\/pbs.twimg.com\/tweet_video_thumb\/CZKLQ7UWIAECtYe.png","media_url_https":"https:\/\/pbs.twimg.com\/tweet_video_thumb\/CZKLQ7UWIAECtYe.png","url":"https:\/\/t.co\/Gtz15AFz6K","display_url":"pic.twitter.com\/Gtz15AFz6K","expanded_url":"http:\/\/twitter.com\/Wotamoron\/status\/689766935270158336\/photo\/1","type":"photo","sizes":{"medium":{"w":256,"h":274,"resize":"fit"},"small":{"w":256,"h":274,"resize":"fit"},"thumb":{"w":150,"h":150,"resize":"crop"},"large":{"w":256,"h":274,"resize":"fit"}},"source_status_id":689766935270158336,"source_status_id_str":"689766935270158336","source_user_id":3079307777,"source_user_id_str":"3079307777"}]},"extended_entities":{"media":[{"id":689766815858302977,"id_str":"689766815858302977","indices":[42,65],"media_url":"http:\/\/pbs.twimg.com\/tweet_video_thumb\/CZKLQ7UWIAECtYe.png","media_url_https":"https:\/\/pbs.twimg.com\/tweet_video_thumb\/CZKLQ7UWIAECtYe.png","url":"https:\/\/t.co\/Gtz15AFz6K","display_url":"pic.twitter.com\/Gtz15AFz6K","expanded_url":"http:\/\/twitter.com\/Wotamoron\/status\/689766935270158336\/photo\/1","type":"animated_gif","sizes":{"medium":{"w":256,"h":274,"resize":"fit"},"small":{"w":256,"h":274,"resize":"fit"},"thumb":{"w":150,"h":150,"resize":"crop"},"large":{"w":256,"h":274,"resize":"fit"}},"source_status_id":689766935270158336,"source_status_id_str":"689766935270158336","source_user_id":3079307777,"source_user_id_str":"3079307777","video_info":{"aspect_ratio":[128,137],"variants":[{"bitrate":0,"content_type":"video\/mp4","url":"https:\/\/pbs.twimg.com\/tweet_video\/CZKLQ7UWIAECtYe.mp4"}]}}]},"favorited":false,"retweeted":false,"possibly_sensitive":false,"lang":"en"},"contributors_enabled":false,"is_translator":false,"is_translation_enabled":false,"profile_background_color":"C0DEED","profile_background_image_url":"http:\/\/abs.twimg.com\/images\/themes\/theme1\/bg.png","profile_background_image_url_https":"https:\/\/abs.twimg.com\/images\/themes\/theme1\/bg.png","profile_background_tile":false,"profile_image_url":"http:\/\/pbs.twimg.com\/profile_images\/1364259938\/image_normal.jpg","profile_image_url_https":"https:\/\/pbs.twimg.com\/profile_images\/1364259938\/image_normal.jpg","profile_banner_url":"https:\/\/pbs.twimg.com\/profile_banners\/303079893\/1376700816","profile_link_color":"0084B4","profile_sidebar_border_color":"C0DEED","profile_sidebar_fill_color":"DDEEF6","profile_text_color":"333333","profile_use_background_image":true,"has_extended_profile":false,"default_profile":true,"default_profile_image":false,"following":false,"follow_request_sent":false,"notifications":false}
