{"id":307725028,"id_str":"307725028","name":"Kaaaaueeee ' ","screen_name":"KaUe_LdF","location":"","profile_location":null,"description":"","url":null,"entities":{"description":{"urls":[]}},"protected":false,"followers_count":565,"friends_count":1816,"listed_count":1,"created_at":"Mon May 30 05:26:35 +0000 2011","favourites_count":19,"utc_offset":10800,"time_zone":"Baghdad","geo_enabled":false,"verified":false,"statuses_count":5387,"lang":"en","status":{"created_at":"Fri Jun 15 03:15:56 +0000 2012","id":213469865145667585,"id_str":"213469865145667585","text":"RT @JosefinaVM Te invitamos a seguir en vivo la trasmisi?n de este evento con la comunidad mazatleca http:\/\/t.co\/FfaLJeLw","source":"\u003ca href=\"https:\/\/dev.twitter.com\/docs\/tfw\" rel=\"nofollow\"\u003eTwitter for Websites\u003c\/a\u003e","truncated":false,"in_reply_to_status_id":null,"in_reply_to_status_id_str":null,"in_reply_to_user_id":null,"in_reply_to_user_id_str":null,"in_reply_to_screen_name":null,"geo":null,"coordinates":null,"place":null,"contributors":null,"is_quote_status":false,"retweet_count":0,"favorite_count":0,"entities":{"hashtags":[],"symbols":[],"user_mentions":[{"screen_name":"JosefinaVM","name":"JosefinaV\u00e1zquezMota","id":41421105,"id_str":"41421105","indices":[3,14]}],"urls":[{"url":"http:\/\/t.co\/FfaLJeLw","expanded_url":"http:\/\/www.livestream.com\/josefinavm","display_url":"livestream.com\/josefinavm","indices":[101,121]}]},"favorited":false,"retweeted":false,"possibly_sensitive":false,"lang":"es"},"contributors_enabled":false,"is_translator":false,"is_translation_enabled":false,"profile_background_color":"000000","profile_background_image_url":"http:\/\/pbs.twimg.com\/profile_background_images\/399359470\/page.jpg","profile_background_image_url_https":"https:\/\/pbs.twimg.com\/profile_background_images\/399359470\/page.jpg","profile_background_tile":true,"profile_image_url":"http:\/\/pbs.twimg.com\/profile_images\/1745369716\/DSC01767_normal.JPG","profile_image_url_https":"https:\/\/pbs.twimg.com\/profile_images\/1745369716\/DSC01767_normal.JPG","profile_link_color":"39F50A","profile_sidebar_border_color":"09E022","profile_sidebar_fill_color":"F20CF2","profile_text_color":"09F225","profile_use_background_image":true,"has_extended_profile":false,"default_profile":false,"default_profile_image":false,"following":false,"follow_request_sent":false,"notifications":false}
