{"id":90169413,"id_str":"90169413","name":"UGIdotNET","screen_name":"ugidotnet","location":"Milan","profile_location":null,"description":"","url":"http:\/\/t.co\/8mViOls0Yl","entities":{"url":{"urls":[{"url":"http:\/\/t.co\/8mViOls0Yl","expanded_url":"http:\/\/www.ugidotnet.org","display_url":"ugidotnet.org","indices":[0,22]}]},"description":{"urls":[]}},"protected":false,"followers_count":750,"friends_count":34,"listed_count":52,"created_at":"Sun Nov 15 14:18:05 +0000 2009","favourites_count":20,"utc_offset":3600,"time_zone":"Rome","geo_enabled":true,"verified":false,"statuses_count":630,"lang":"en","status":{"created_at":"Mon Jan 11 08:43:25 +0000 2016","id":686468445106515968,"id_str":"686468445106515968","text":"\u201cCross Border Portability: novit\u00e0 in Europa per Geo-Blocking e Copyright\u201d #lex101 https:\/\/t.co\/CSWpR6WO4B","source":"\u003ca href=\"http:\/\/itunes.apple.com\/us\/app\/twitter\/id409789998?mt=12\" rel=\"nofollow\"\u003eTwitter for Mac\u003c\/a\u003e","truncated":false,"in_reply_to_status_id":null,"in_reply_to_status_id_str":null,"in_reply_to_user_id":null,"in_reply_to_user_id_str":null,"in_reply_to_screen_name":null,"geo":null,"coordinates":null,"place":null,"contributors":null,"is_quote_status":false,"retweet_count":3,"favorite_count":0,"entities":{"hashtags":[{"text":"lex101","indices":[74,81]}],"symbols":[],"user_mentions":[],"urls":[{"url":"https:\/\/t.co\/CSWpR6WO4B","expanded_url":"http:\/\/blogs.ugidotnet.org\/lex101\/archive\/2016\/01\/09\/cross-border-portability-novita-in-europa-per-geo-blocking-e-copyright.aspx","display_url":"blogs.ugidotnet.org\/lex101\/archive\u2026","indices":[82,105]}]},"favorited":false,"retweeted":false,"possibly_sensitive":false,"lang":"it"},"contributors_enabled":false,"is_translator":false,"is_translation_enabled":false,"profile_background_color":"C0DEED","profile_background_image_url":"http:\/\/abs.twimg.com\/images\/themes\/theme1\/bg.png","profile_background_image_url_https":"https:\/\/abs.twimg.com\/images\/themes\/theme1\/bg.png","profile_background_tile":false,"profile_image_url":"http:\/\/pbs.twimg.com\/profile_images\/1139380310\/ugidotnet_normal.png","profile_image_url_https":"https:\/\/pbs.twimg.com\/profile_images\/1139380310\/ugidotnet_normal.png","profile_link_color":"0084B4","profile_sidebar_border_color":"C0DEED","profile_sidebar_fill_color":"DDEEF6","profile_text_color":"333333","profile_use_background_image":true,"has_extended_profile":false,"default_profile":true,"default_profile_image":false,"following":false,"follow_request_sent":false,"notifications":false}
