{"created_at":"Thu Oct 20 03:34:54 +0000 2011","id":126863938339094531,"id_str":"126863938339094531","text":"#FB no es mi amigo, por eso mejor #Twitter , al menos ahorita","source":"\u003ca href=\"erased_49624\" rel=\"nofollow\"\u003eerased_49624\u003c\/a\u003e","truncated":false,"in_reply_to_status_id":null,"in_reply_to_status_id_str":null,"in_reply_to_user_id":null,"in_reply_to_user_id_str":null,"in_reply_to_screen_name":null,"user":{"id":171570538,"id_str":"171570538","name":"Alejandra S\u00e1nchez","screen_name":"alle_sanchez","location":"","description":"So\u00f1ar, amar, creer, vivir, brincar, cantar, leer!! Seguir conociendo, seguir creciendo...","url":null,"entities":{"description":{"urls":[]}},"protected":false,"followers_count":422,"friends_count":508,"listed_count":1,"created_at":"Tue Jul 27 17:18:43 +0000 2010","favourites_count":507,"utc_offset":-21600,"time_zone":"Central Time (US & Canada)","geo_enabled":true,"verified":false,"statuses_count":23617,"lang":"es","contributors_enabled":false,"is_translator":false,"is_translation_enabled":false,"profile_background_color":"1DDEAE","profile_background_image_url":"http:\/\/pbs.twimg.com\/profile_background_images\/161381016\/j211.jpg","profile_background_image_url_https":"https:\/\/pbs.twimg.com\/profile_background_images\/161381016\/j211.jpg","profile_background_tile":true,"profile_image_url":"http:\/\/pbs.twimg.com\/profile_images\/3752973346\/479b84f9946a5374e0b16744fb39d2bf_normal.jpeg","profile_image_url_https":"https:\/\/pbs.twimg.com\/profile_images\/3752973346\/479b84f9946a5374e0b16744fb39d2bf_normal.jpeg","profile_banner_url":"https:\/\/pbs.twimg.com\/profile_banners\/171570538\/1401209764","profile_link_color":"045370","profile_sidebar_border_color":"15D98B","profile_sidebar_fill_color":"0CE6D4","profile_text_color":"332533","profile_use_background_image":true,"has_extended_profile":false,"default_profile":false,"default_profile_image":false,"following":false,"follow_request_sent":false,"notifications":false},"geo":null,"coordinates":null,"place":null,"contributors":null,"is_quote_status":false,"retweet_count":0,"favorite_count":0,"entities":{"hashtags":[{"text":"FB","indices":[0,3]},{"text":"Twitter","indices":[34,42]}],"symbols":[],"user_mentions":[],"urls":[]},"favorited":false,"retweeted":false,"lang":"es"}
