{"created_at":"Thu Oct 20 03:40:20 +0000 2011","id":126865304277090304,"id_str":"126865304277090304","text":"@lorenbsas @telerinonline @VeroTurismo @elisafn @arielmun @matchpoint20 ah si! ya es hora, pero #Twitter me tienta tanto! me encanta!","source":"\u003ca href=\"http:\/\/twitter.com\" rel=\"nofollow\"\u003eTwitter Web Client\u003c\/a\u003e","truncated":false,"in_reply_to_status_id":126839490017894400,"in_reply_to_status_id_str":"126839490017894400","in_reply_to_user_id":159966136,"in_reply_to_user_id_str":"159966136","in_reply_to_screen_name":"lorenbsas","user":{"id":208575588,"id_str":"208575588","name":"Gabs","screen_name":"DraGEF","location":"London","description":"Del escuchar procede la sabidur\u00eda, y del hablar el arrepentimiento.","url":null,"entities":{"description":{"urls":[]}},"protected":false,"followers_count":1842,"friends_count":1301,"listed_count":83,"created_at":"Wed Oct 27 14:38:57 +0000 2010","favourites_count":80437,"utc_offset":-10800,"time_zone":"Buenos Aires","geo_enabled":true,"verified":false,"statuses_count":84685,"lang":"en","contributors_enabled":false,"is_translator":false,"is_translation_enabled":false,"profile_background_color":"000000","profile_background_image_url":"http:\/\/pbs.twimg.com\/profile_background_images\/665769399719239680\/lcjQfJ1n.png","profile_background_image_url_https":"https:\/\/pbs.twimg.com\/profile_background_images\/665769399719239680\/lcjQfJ1n.png","profile_background_tile":true,"profile_image_url":"http:\/\/pbs.twimg.com\/profile_images\/657972269545824256\/5UbzvGW0_normal.jpg","profile_image_url_https":"https:\/\/pbs.twimg.com\/profile_images\/657972269545824256\/5UbzvGW0_normal.jpg","profile_banner_url":"https:\/\/pbs.twimg.com\/profile_banners\/208575588\/1446926307","profile_link_color":"4A913C","profile_sidebar_border_color":"FFFFFF","profile_sidebar_fill_color":"FA5D66","profile_text_color":"442E52","profile_use_background_image":true,"has_extended_profile":false,"default_profile":false,"default_profile_image":false,"following":false,"follow_request_sent":false,"notifications":false},"geo":null,"coordinates":null,"place":null,"contributors":null,"is_quote_status":false,"retweet_count":0,"favorite_count":0,"entities":{"hashtags":[{"text":"Twitter","indices":[96,104]}],"symbols":[],"user_mentions":[{"screen_name":"lorenbsas","name":"#NiUnaMenos Lorena","id":159966136,"id_str":"159966136","indices":[0,10]},{"screen_name":"telerinonline","name":"andrea santos mu\u00f1oz","id":19291684,"id_str":"19291684","indices":[11,25]},{"screen_name":"elisafn","name":"Elisa Nievas","id":37471779,"id_str":"37471779","indices":[39,47]},{"screen_name":"arielmun","name":"ArielMun\u2122","id":124577375,"id_str":"124577375","indices":[48,57]},{"screen_name":"matchpoint20","name":"\u062e\u064a\u0631\u064a \u0627\u0644\u0645\u0633\u064a\u062d\u0644\u060c","id":4529146877,"id_str":"4529146877","indices":[58,71]}],"urls":[]},"favorited":false,"retweeted":false,"lang":"es"}
